Metadata-Version: 2.1
Name: infrasonar-appliance
Version: 0.2.2
Summary: InfraSonar Appliance Manager
Home-page: https://github.com/infrasonar/appliance-manager
Author: Jeroen van der Heijden
Author-email: jeroen@cesbit.com
License: GPLv3
Keywords: infrasonar monitoring toolkit util
Classifier: Development Status :: 4 - Beta
Classifier: Intended Audience :: Developers
Classifier: License :: OSI Approved :: MIT License
Classifier: Programming Language :: Python :: 3.7
Classifier: Programming Language :: Python :: 3.8
Classifier: Programming Language :: Python :: 3.9
Classifier: Programming Language :: Python :: 3.10
Classifier: Programming Language :: Python :: 3.11
Classifier: Programming Language :: Python :: 3.12
License-File: LICENSE
Requires-Dist: aiohttp
Requires-Dist: pyyaml
Requires-Dist: configobj
Requires-Dist: setproctitle
